setup.py
funniest/__init__.py
new123.egg-info/PKG-INFO
new123.egg-info/SOURCES.txt
new123.egg-info/dependency_links.txt
new123.egg-info/not-zip-safe
new123.egg-info/top_level.txt