Metadata-Version: 1.0
Name: new123
Version: 0.1
Summary: for print helloworlsd
Home-page: UNKNOWN
Author: superman
Author-email: jaga@gmail.com
License: MIT
Platform: UNKNOWN
